SimpleDB/__init__.py
SimpleDB/main.py
pyEasyDbApi-0.2.1.dist-info/LICENSE
pyEasyDbApi-0.2.1.dist-info/METADATA
pyEasyDbApi-0.2.1.dist-info/WHEEL
pyEasyDbApi-0.2.1.dist-info/top_level.txt
pyEasyDbApi-0.2.1.dist-info/RECORD
